{"id": {"module": "builtins", "name": "str", "type": "instance", "uuid": "builtins.str", "hash": "0x7efe97c82eb0"}, "payload.AllowIPNPayment": {"module": "builtins", "name": "bool", "type": "instance", "uuid": "builtins.bool", "hash": "0x7eff67eab280"}, "payload.AllowOnlinePayment": {"module": "builtins", "name": "bool", "type": "instance", "uuid": "builtins.bool", "hash": "0x7eff67eab280"}, "payload.AllowOnlineCreditCardPayment": {"module": "builtins", "name": "bool", "type": "instance", "uuid": "builtins.bool", "hash": "0x7eff67eab280"}, "payload.AllowOnlineACHPayment": {"module": "builtins", "name": "bool", "type": "instance", "uuid": "builtins.bool", "hash": "0x7eff67eab280"}, "payload.domain": {"module": "builtins", "name": "str", "type": "instance", "uuid": "builtins.str", "hash": "0x7efe97c80330"}, "payload.sparse": {"module": "builtins", "name": "bool", "type": "instance", "uuid": "builtins.bool", "hash": "0x7eff67eab280"}, "payload.Id": {"module": "builtins", "name": "str", "type": "instance", "uuid": "builtins.str", "hash": "0x7efe97c82eb0"}, "payload.SyncToken": {"module": "builtins", "name": "str", "type": "instance", "uuid": "builtins.str", "hash": "0x7eff67726670"}, "payload.MetaData.CreateTime": {"module": "builtins", "name": "str", "type": "instance", "uuid": "builtins.str", "hash": "0x7efe99009930"}, "payload.MetaData.LastModifiedByRef.value": {"module": "builtins", "name": "str", "type": "instance", "uuid": "builtins.str", "hash": "0x7efe9900b280"}, "payload.MetaData.LastUpdatedTime": {"module": "builtins", "name": "str", "type": "instance", "uuid": "builtins.str", "hash": "0x7efe99008a30"}, "payload.CustomField": {"module": "builtins", "name": "list", "type": "instance", "uuid": "builtins.list", "hash": "0x7efe99197980", "variable_type": "iterable"}, "payload.DocNumber": {"module": "builtins", "name": "str", "type": "instance", "uuid": "builtins.str", "hash": "0x7efe97c82470"}, "payload.TxnDate": {"module": "builtins", "name": "str", "type": "instance", "uuid": "builtins.str", "hash": "0x7efe97c810b0"}, "payload.CurrencyRef.value": {"module": "builtins", "name": "str", "type": "instance", "uuid": "builtins.str", "hash": "0x7efe97c81d70"}, "payload.CurrencyRef.name": {"module": "builtins", "name": "str", "type": "instance", "uuid": "builtins.str", "hash": "0x7efe9900ad30"}, "payload.LinkedTxn.0.TxnId": {"module": "builtins", "name": "str", "type": "instance", "uuid": "builtins.str", "hash": "0x7efe97c80ff0"}, "payload.LinkedTxn.0.TxnType": {"module": "builtins", "name": "str", "type": "instance", "uuid": "builtins.str", "hash": "0x7efe97c806b0"}, "payload.LinkedTxn.0": {"module": "builtins", "name": "dict", "type": "instance", "uuid": "builtins.dict", "hash": "0x7efe97c82380"}, "payload.LinkedTxn": {"module": "builtins", "name": "list", "type": "instance", "uuid": "builtins.list", "hash": "0x7efe988ba100", "variable_type": "iterable"}, "payload.Line.0.Id": {"module": "builtins", "name": "str", "type": "instance", "uuid": "builtins.str", "hash": "0x7eff67726670"}, "payload.Line.0.LineNum": {"module": "builtins", "name": "int", "type": "instance", "uuid": "builtins.int", "hash": "0x7eff677440f0"}, "payload.Line.0.Description": {"module": "builtins", "name": "str", "type": "instance", "uuid": "builtins.str", "hash": "0x7efe99008b70"}, "payload.Line.0.Amount": {"module": "builtins", "name": "float", "type": "instance", "uuid": "builtins.float", "hash": "0x7efe979d8790"}, "payload.Line.0.DetailType": {"module": "builtins", "name": "str", "type": "instance", "uuid": "builtins.str", "hash": "0x7efe9900a1f0"}, "payload.Line.0.SalesItemLineDetail.ItemRef.value": {"module": "builtins", "name": "str", "type": "instance", "uuid": "builtins.str", "hash": "0x7eff67573df0"}, "payload.Line.0.SalesItemLineDetail.ItemRef.name": {"module": "builtins", "name": "str", "type": "instance", "uuid": "builtins.str", "hash": "0x7efe97c81a30"}, "payload.Line.0.SalesItemLineDetail.ItemRef": {"module": "builtins", "name": "dict", "type": "instance", "uuid": "builtins.dict", "hash": "0x7efe97c82a40"}, "payload.Line.0.SalesItemLineDetail.UnitPrice": {"module": "builtins", "name": "int", "type": "instance", "uuid": "builtins.int", "hash": "0x7eff67744350"}, "payload.Line.0.SalesItemLineDetail.Qty": {"module": "builtins", "name": "int", "type": "instance", "uuid": "builtins.int", "hash": "0x7eff67744150"}, "payload.Line.0.SalesItemLineDetail.ItemAccountRef.value": {"module": "builtins", "name": "str", "type": "instance", "uuid": "builtins.str", "hash": "0x7efe97c83b30"}, "payload.Line.0.SalesItemLineDetail.ItemAccountRef.name": {"module": "builtins", "name": "str", "type": "instance", "uuid": "builtins.str", "hash": "0x7efe9900a3d0"}, "payload.Line.0.SalesItemLineDetail.ItemAccountRef": {"module": "builtins", "name": "dict", "type": "instance", "uuid": "builtins.dict", "hash": "0x7efe97c822c0"}, "payload.Line.0.SalesItemLineDetail.TaxCodeRef.value": {"module": "builtins", "name": "str", "type": "instance", "uuid": "builtins.str", "hash": "0x7efe97c81270"}, "payload.Line.0.SalesItemLineDetail.TaxCodeRef": {"module": "builtins", "name": "dict", "type": "instance", "uuid": "builtins.dict", "hash": "0x7efe97c82680"}, "payload.Line.0.SalesItemLineDetail": {"module": "builtins", "name": "dict", "type": "instance", "uuid": "builtins.dict", "hash": "0x7efe97c83cc0"}, "payload.Line.0.CustomExtensions": {"module": "builtins", "name": "list", "type": "instance", "uuid": "builtins.list", "hash": "0x7efe97acabc0", "variable_type": "iterable"}, "payload.Line.0": {"module": "builtins", "name": "dict", "type": "instance", "uuid": "builtins.dict", "hash": "0x7efe97c81e00"}, "payload.Line.1.Amount": {"module": "builtins", "name": "float", "type": "instance", "uuid": "builtins.float", "hash": "0x7efe979d89d0"}, "payload.Line.1.DetailType": {"module": "builtins", "name": "str", "type": "instance", "uuid": "builtins.str", "hash": "0x7efe9900beb0"}, "payload.Line.1.SubTotalLineDetail": {"module": "builtins", "name": "dict", "type": "instance", "uuid": "builtins.dict", "hash": "0x7efe97c80580"}, "payload.Line.1": {"module": "builtins", "name": "dict", "type": "instance", "uuid": "builtins.dict", "hash": "0x7efe97c83b00"}, "payload.Line": {"module": "builtins", "name": "list", "type": "instance", "uuid": "builtins.list", "hash": "0x7efe98c13c40", "variable_type": "iterable"}, "payload.TxnTaxDetail.TotalTax": {"module": "builtins", "name": "int", "type": "instance", "uuid": "builtins.int", "hash": "0x7eff677440d0"}, "payload.CustomerRef.value": {"module": "builtins", "name": "str", "type": "instance", "uuid": "builtins.str", "hash": "0x7efe97c821b0"}, "payload.CustomerRef.name": {"module": "builtins", "name": "str", "type": "instance", "uuid": "builtins.str", "hash": "0x7efe99009e30"}, "payload.CustomerMemo.value": {"module": "builtins", "name": "str", "type": "instance", "uuid": "builtins.str", "hash": "0x7efe97947050"}, "payload.BillAddr.Id": {"module": "builtins", "name": "str", "type": "instance", "uuid": "builtins.str", "hash": "0x7efe97c81630"}, "payload.BillAddr.Line1": {"module": "builtins", "name": "str", "type": "instance", "uuid": "builtins.str", "hash": "0x7efe9900b000"}, "payload.BillAddr.Line2": {"module": "builtins", "name": "str", "type": "instance", "uuid": "builtins.str", "hash": "0x7efe98612d80"}, "payload.BillAddr.Line3": {"module": "builtins", "name": "str", "type": "instance", "uuid": "builtins.str", "hash": "0x7efe97c818b0"}, "payload.BillAddr.Line4": {"module": "builtins", "name": "str", "type": "instance", "uuid": "builtins.str", "hash": "0x7efe97bf2d80"}, "payload.BillAddr.Lat": {"module": "builtins", "name": "str", "type": "instance", "uuid": "builtins.str", "hash": "0x7efe97c83470"}, "payload.BillAddr.Long": {"module": "builtins", "name": "str", "type": "instance", "uuid": "builtins.str", "hash": "0x7efe97c81af0"}, "payload.ShipAddr.Id": {"module": "builtins", "name": "str", "type": "instance", "uuid": "builtins.str", "hash": "0x7efe97c81430"}, "payload.ShipAddr.Line1": {"module": "builtins", "name": "str", "type": "instance", "uuid": "builtins.str", "hash": "0x7efe97c83e30"}, "payload.ShipAddr.City": {"module": "builtins", "name": "str", "type": "instance", "uuid": "builtins.str", "hash": "0x7efe97c80b70"}, "payload.ShipAddr.CountrySubDivisionCode": {"module": "builtins", "name": "str", "type": "instance", "uuid": "builtins.str", "hash": "0x7efe97c811b0"}, "payload.ShipAddr.PostalCode": {"module": "builtins", "name": "str", "type": "instance", "uuid": "builtins.str", "hash": "0x7efe97c80670"}, "payload.ShipAddr.Lat": {"module": "builtins", "name": "str", "type": "instance", "uuid": "builtins.str", "hash": "0x7efe97c82d70"}, "payload.ShipAddr.Long": {"module": "builtins", "name": "str", "type": "instance", "uuid": "builtins.str", "hash": "0x7efe97c81170"}, "payload.FreeFormAddress": {"module": "builtins", "name": "bool", "type": "instance", "uuid": "builtins.bool", "hash": "0x7eff67eab2a0"}, "payload.SalesTermRef.value": {"module": "builtins", "name": "str", "type": "instance", "uuid": "builtins.str", "hash": "0x7eff675737b0"}, "payload.SalesTermRef.name": {"module": "builtins", "name": "str", "type": "instance", "uuid": "builtins.str", "hash": "0x7efe97c82770"}, "payload.DueDate": {"module": "builtins", "name": "str", "type": "instance", "uuid": "builtins.str", "hash": "0x7efe97c80fb0"}, "payload.TotalAmt": {"module": "builtins", "name": "float", "type": "instance", "uuid": "builtins.float", "hash": "0x7efe979d8a90"}, "payload.ApplyTaxAfterDiscount": {"module": "builtins", "name": "bool", "type": "instance", "uuid": "builtins.bool", "hash": "0x7eff67eab280"}, "payload.PrintStatus": {"module": "builtins", "name": "str", "type": "instance", "uuid": "builtins.str", "hash": "0x7efe97c80870"}, "payload.EmailStatus": {"module": "builtins", "name": "str", "type": "instance", "uuid": "builtins.str", "hash": "0x7efe97c829b0"}, "payload.BillEmail.Address": {"module": "builtins", "name": "str", "type": "instance", "uuid": "builtins.str", "hash": "0x7efe97bf0bc0"}, "payload.Balance": {"module": "builtins", "name": "int", "type": "instance", "uuid": "builtins.int", "hash": "0x7eff677440d0"}, "ingested_at_utc": {"module": "datetime", "name": "datetime", "type": "instance", "uuid": "datetime.datetime", "hash": "0x7efe987df600", "variable_type": "custom_object", "path": "/home/src/mage_data/scheduler/pipelines/qb_invoices_backfill/.variables/invoices_extract/output_5/ingested_at_utc/object.joblib"}, "extract_window_start_utc": {"module": "datetime", "name": "datetime", "type": "instance", "uuid": "datetime.datetime", "hash": "0x7efe987df7b0", "variable_type": "custom_object", "path": "/home/src/mage_data/scheduler/pipelines/qb_invoices_backfill/.variables/invoices_extract/output_5/extract_window_start_utc/object.joblib"}, "extract_window_end_utc": {"module": "datetime", "name": "datetime", "type": "instance", "uuid": "datetime.datetime", "hash": "0x7efe987dffc0", "variable_type": "custom_object", "path": "/home/src/mage_data/scheduler/pipelines/qb_invoices_backfill/.variables/invoices_extract/output_5/extract_window_end_utc/object.joblib"}, "page_number": {"module": "builtins", "name": "int", "type": "instance", "uuid": "builtins.int", "hash": "0x7eff677440f0"}, "page_size": {"module": "builtins", "name": "int", "type": "instance", "uuid": "builtins.int", "hash": "0x7efe978f24d0"}, "request_payload.query": {"module": "builtins", "name": "str", "type": "instance", "uuid": "builtins.str", "hash": "0x7efe97946bf0"}}